rsdiv/__init__.py
rsdiv/aggregation/__init__.py
rsdiv/aggregation/pmf.py
rsdiv/aggregation/rank_product.py
rsdiv/dataset/__init__.py
rsdiv/dataset/base.py
rsdiv/dataset/movielens_100k.py
rsdiv/dataset/movielens_1m.py
rsdiv/diversity/__init__.py
rsdiv/diversity/base.py
rsdiv/diversity/mmr.py
rsdiv/diversity/ssd.py
rsdiv/embedding/__init__.py
rsdiv/embedding/base.py
rsdiv/embedding/cc.en.300.movielens.pkl
rsdiv/embedding/fasttext_embedding.py
rsdiv/encoding/__init__.py
rsdiv/encoding/base.py
rsdiv/encoding/geo_encoder.py
rsdiv/encoding/geojson-counties-fips.json
rsdiv/evaluation/__init__.py
rsdiv/evaluation/diversity_metrics.py
rsdiv/evaluation/ranking_distance.py
rsdiv/evaluation/ranking_metrics.py
rsdiv/evaluation/relevance_metrics.py
rsdiv/optimization/__init__.py
rsdiv/optimization/optimizer.py
rsdiv/recommenders/__init__.py
rsdiv/recommenders/base.py
rsdiv/recommenders/fm.py
rsdiv/recommenders/ials.py
rsdiv-0.2.7.1.dist-info/LICENSE
rsdiv-0.2.7.1.dist-info/METADATA
rsdiv-0.2.7.1.dist-info/WHEEL
rsdiv-0.2.7.1.dist-info/top_level.txt
rsdiv-0.2.7.1.dist-info/RECORD
