Metadata-Version: 2.1
Name: rsdiv
Version: 0.2.7.1
Home-page: https://github.com/smartnews/rsdiv
Author: Yin Cheng
Author-email: yin.sjtu@gmail.com
Requires-Python: >=3.8
License-File: LICENSE
Requires-Dist: numpy (>=1.23.3)
Requires-Dist: pandas (>=1.5.0)
Requires-Dist: scipy (>=1.9.1)
Requires-Dist: lightfm (>=1.16)
Requires-Dist: scikit-learn (>=1.1.2)
Requires-Dist: matplotlib (>=3.6.0)
Requires-Dist: plotly (>=5.10.0)
Requires-Dist: implicit (==0.6.2)
